{
	"$schema": "https://biomejs.dev/schemas/1.9.4/schema.json",
	"linter": {
		"enabled": true,
		"rules": {
			"recommended": true,
			"suspicious": {
				"noExplicitAny": "off",
				"noAsyncPromiseExecutor": "off"
			},
			"style": {
				"noParameterAssign": "off",
				"useImportType": "off"
			},
			"complexity": {
				"noStaticOnlyClass": "off",
				"useLiteralKeys": "off",
				"noForEach": "off"
			}
		},
		"ignore": []
	},
	"formatter": {
		"enabled": true,
		"formatWithErrors": false,
		"indentStyle": "tab",
		"indentWidth": 2,
		"lineWidth": 150,
		"ignore": []
	},
	"javascript": {
		"formatter": {
			"quoteStyle": "double",
			"trailingCommas": "none",
			"semicolons": "asNeeded"
		},
		"parser": {
			"unsafeParameterDecoratorsEnabled": true
		}
	},
	"files": {
		"ignore": ["./.vscode*"],
		"maxSize": 31457280
	}
}
